textverified/__init__.py
textverified/account_api.py
textverified/action.py
textverified/billing_cycle_api.py
textverified/exceptions.py
textverified/paginated_list.py
textverified/reservations_api.py
textverified/sales_api.py
textverified/services_api.py
textverified/sms_api.py
textverified/textverified.py
textverified/verifications_api.py
textverified/wake_api.py
textverified/data/__init__.py
textverified/data/dtypes.py
textverified-0.1.0a1.dist-info/METADATA
textverified-0.1.0a1.dist-info/WHEEL
textverified-0.1.0a1.dist-info/top_level.txt
textverified-0.1.0a1.dist-info/RECORD
