Metadata-Version: 2.4
Name: textverified
Version: 0.1.0a1
Summary: Python wrapper for the TextVerified API
Home-page: https://textverified.com
Download-URL: https://pypi.org/project/textverified/#files
Author: Textverified
License: MIT
Project-URL: Homepage, https://textverified.com
Project-URL: Download, https://pypi.org/project/textverified/#files
Project-URL: Documentation, https://textverified-python.readthedocs.io/en/latest/
Project-URL: Source, https://github.com/Westbold/PythonClient
Project-URL: Issues, https://github.com/Westbold/PythonClient/issues
Keywords: Textverified,Verification,Web Scraping,API,webhook,python
Requires-Dist: requests>=2.31.0
Requires-Dist: urllib3>=1.26.20
Requires-Dist: python-dateutil>=2.9.0
Provides-Extra: dev
Requires-Dist: black==23.3.0; extra == "dev"
Requires-Dist: pytest>=7.4.4; extra == "dev"
Requires-Dist: pytest-cov>=4.1.0; extra == "dev"
Requires-Dist: networkx>=3.1; extra == "dev"
Requires-Dist: build>=1.1.1; extra == "dev"
Requires-Dist: tomli>=2.0.1; extra == "dev"
Provides-Extra: docs
Requires-Dist: sphinx>=5.3.0; extra == "docs"
Requires-Dist: sphinx-rtd-theme>=1.3.0; extra == "docs"
Dynamic: download-url
Dynamic: home-page
